setup.py
distributions/Binomialdistribution.py
distributions/Gaussiandistribution.py
distributions/Generaldistribution.py
distributions/__init__.py
p6_probability.egg-info/PKG-INFO
p6_probability.egg-info/SOURCES.txt
p6_probability.egg-info/dependency_links.txt
p6_probability.egg-info/not-zip-safe
p6_probability.egg-info/top_level.txt